.gitignore
CHANGES.txt
README.rst
setup.py
tox.ini
configless/__init__.py
configless/interfaces.py
configless/langhelper.py
configless.egg-info/PKG-INFO
configless.egg-info/SOURCES.txt
configless.egg-info/dependency_links.txt
configless.egg-info/entry_points.txt
configless.egg-info/not-zip-safe
configless.egg-info/requires.txt
configless.egg-info/top_level.txt
configless/tests/__init__.py
configless/tests/test_configurator.py